rkb_probability/Binomialdistribution.py
rkb_probability/Gaussiandistribution.py
rkb_probability/Generaldistribution.py
rkb_probability/__init__.py
rkb_probability-1.6.dist-info/DESCRIPTION.rst
rkb_probability-1.6.dist-info/METADATA
rkb_probability-1.6.dist-info/RECORD
rkb_probability-1.6.dist-info/WHEEL
rkb_probability-1.6.dist-info/metadata.json
rkb_probability-1.6.dist-info/top_level.txt
