Metadata-Version: 2.0
Name: rkb-probability
Version: 1.6
Summary: Gaussian and Bionomial distributions
Home-page: UNKNOWN
Author: Raj Kumar Barmon
Author-email: apu.rajkumar1@gmail.com
License: UNKNOWN
Platform: UNKNOWN
